CEDA
