Metadata-Version: 2.1
Name: CEDApy
Version: 0.3.2
Summary: UNKNOWN
Home-page: https://github.com/TerenceLiu98/CEDApy
Author: TerenceCKLau
Author-email: terenceliu1012@outlook.com
License: MIT
Keywords: quantitative economic data
Platform: UNKNOWN
Classifier: Programming Language :: Python :: 3.6
Classifier: Programming Language :: Python :: 3.7
Classifier: Programming Language :: Python :: 3.8
Classifier: Programming Language :: Python :: 3.9
Classifier: License :: OSI Approved :: MIT License
Classifier: Operating System :: OS Independent
Requires-Python: >=3.6
License-File: LICENSE
